sonytech/__init__.py
sonytech/main.py
sonytech-0.1.0.dist-info/METADATA
sonytech-0.1.0.dist-info/WHEEL
sonytech-0.1.0.dist-info/top_level.txt
sonytech-0.1.0.dist-info/RECORD
