Metadata-Version: 2.1
Name: sonytech
Version: 0.1.0
Requires-Dist: pyttsx3
Requires-Dist: SpeechRecognition
Requires-Dist: ollama
